JynParser/__init__.py
JynParser/module.py
JynParser-1.dist-info/LICENSE
JynParser-1.dist-info/METADATA
JynParser-1.dist-info/WHEEL
JynParser-1.dist-info/top_level.txt
JynParser-1.dist-info/RECORD
