Metadata-Version: 2.1
Name: JynParser
Version: 1
Summary: JynParser Python Parser Module
Home-page: https://github.com/Jynoqtra/JynPopMod
Author: Jynoqtra
Author-email: Jynoqtra@gmail.com
Classifier: Programming Language :: Python :: 3
Classifier: License :: Other/Proprietary License
Classifier: Intended Audience :: Developers
License-File: LICENSE
